[
  {
    "id": "1",
    "modelo": "modelo-conteudo.psd",
    "titulo": [
      "VITAMINA D",
      "Para quê?"
    ],
    "dirBase": "/base/",
    "imagem": {
      "posicao": "C",
      "girar": "N",
      "nome": "1.png"
    },
    "dirExportar": "/export/[ASSINATURA]/mes-001/semana-1/1-segunda/",
    "prefixo": "P3-C0001"
  },
  {
    "id": "2",
    "modelo": "modelo-conteudo.psd",
    "titulo": [
      "COMO MANTER O PESO",
      "Para sempre"
    ],
    "dirBase": "/base/",
    "imagem": {
      "posicao": "C",
      "girar": "N",
      "nome": "2.png"
    },
    "dirExportar": "/export/[ASSINATURA]/mes-001/semana-1/2-terça/",
    "prefixo": "P3-C0002"
  },
  {
    "id": "3",
    "modelo": "modelo-conteudo.psd",
    "titulo": [
      "EMAGRECER SEM PARAR",
      "De beber"
    ],
    "dirBase": "/base/",
    "imagem": {
      "posicao": "C",
      "girar": "N",
      "nome": "3.png"
    },
    "dirExportar": "/export/[ASSINATURA]/mes-001/semana-1/3-quarta/",
    "prefixo": "P3-C0003"
  },
  {
    "id": "4",
    "modelo": "modelo-conteudo.psd",
    "titulo": [
      "FIBRAS AJUDAM",
      "Emagrecer?"
    ],
    "dirBase": "/base/",
    "imagem": {
      "posicao": "C",
      "girar": "N",
      "nome": "4.png"
    },
    "dirExportar": "/export/[ASSINATURA]/mes-001/semana-1/4-quinta/",
    "prefixo": "P3-C0004"
  },
  {
    "id": "5",
    "modelo": "modelo-conteudo.psd",
    "titulo": [
      "EU MEREÇO O",
      "Dia do lixo"
    ],
    "dirBase": "/base/",
    "imagem": {
      "posicao": "C",
      "girar": "N",
      "nome": "5.png"
    },
    "dirExportar": "/export/[ASSINATURA]/mes-001/semana-1/5-sexta/",
    "prefixo": "P3-C0005"
  },
  {
    "id": "6",
    "modelo": "modelo-conteudo.psd",
    "titulo": [
      "DEVO COMER",
      "Proteína?"
    ],
    "dirBase": "/base/",
    "imagem": {
      "posicao": "C",
      "girar": "N",
      "nome": "6.png"
    },
    "dirExportar": "/export/[ASSINATURA]/mes-001/semana-1/6-sábado/",
    "prefixo": "P3-C0006"
  },
  {
    "id": "7",
    "modelo": "modelo-conteudo.psd",
    "titulo": [
      "VOCÊ TEM MEDO DO",
      "Carboidrato?"
    ],
    "dirBase": "/base/",
    "imagem": {
      "posicao": "C",
      "girar": "N",
      "nome": "7.png"
    },
    "dirExportar": "/export/[ASSINATURA]/mes-001/semana-1/7-domingo/",
    "prefixo": "P3-C0007"
  },
  {
    "id": "8",
    "modelo": "modelo-conteudo.psd",
    "titulo": [
      "SE",
      "Movimente"
    ],
    "dirBase": "/base/",
    "imagem": {
      "posicao": "E",
      "girar": "S",
      "nome": "8.jpg"
    },
    "dirExportar": "/export/[ASSINATURA]/mes-001/semana-2/1-segunda/",
    "prefixo": "P3-C0008"
  },
  {
    "id": "9",
    "modelo": "modelo-conteudo.psd",
    "titulo": [
      "APENAS",
      "Comece"
    ],
    "dirBase": "/base/",
    "imagem": {
      "posicao": "E",
      "girar": "S",
      "nome": "9.jpg"
    },
    "dirExportar": "/export/[ASSINATURA]/mes-001/semana-2/2-terça/",
    "prefixo": "P3-C0009"
  },
  {
    "id": "10",
    "modelo": "modelo-conteudo.psd",
    "titulo": [
      "OBJETIVO",
      "Claro"
    ],
    "dirBase": "/base/",
    "imagem": {
      "posicao": "E",
      "girar": "N",
      "nome": "10.png"
    },
    "dirExportar": "/export/[ASSINATURA]/mes-001/semana-2/3-quarta/",
    "prefixo": "P3-C0010"
  },
  {
    "id": "11",
    "modelo": "modelo-conteudo.psd",
    "titulo": [
      "ATIVIDADE FÍSICA x",
      "Corpo controlado"
    ],
    "dirBase": "/base/",
    "imagem": {
      "posicao": "C",
      "girar": "N",
      "nome": "11.jpg"
    },
    "dirExportar": "/export/[ASSINATURA]/mes-001/semana-2/4-quinta/",
    "prefixo": "P3-C0011"
  },
  {
    "id": "12",
    "modelo": "modelo-conteudo.psd",
    "titulo": [
      "METAS",
      "Alcançadas"
    ],
    "dirBase": "/base/",
    "imagem": {
      "posicao": "E",
      "girar": "N",
      "nome": "12.png"
    },
    "dirExportar": "/export/[ASSINATURA]/mes-001/semana-2/5-sexta/",
    "prefixo": "P3-C0012"
  },
  {
    "id": "13",
    "modelo": "modelo-conteudo.psd",
    "titulo": [
      "VISITE SEU",
      "Médico"
    ],
    "dirBase": "/base/",
    "imagem": {
      "posicao": "C",
      "girar": "N",
      "nome": "13.png"
    },
    "dirExportar": "/export/[ASSINATURA]/mes-001/semana-2/6-sábado/",
    "prefixo": "P3-C0013"
  },
  {
    "id": "14",
    "modelo": "modelo-conteudo.psd",
    "titulo": [
      "PASSO A",
      "Passo"
    ],
    "dirBase": "/base/",
    "imagem": {
      "posicao": "E",
      "girar": "N",
      "nome": "14.png"
    },
    "dirExportar": "/export/[ASSINATURA]/mes-001/semana-2/7-domingo/",
    "prefixo": "P3-C0014"
  },
  {
    "id": "15",
    "modelo": "modelo-conteudo.psd",
    "titulo": [
      "DEVAGAR E",
      "Sempre"
    ],
    "dirBase": "/base/",
    "imagem": {
      "posicao": "E",
      "girar": "S",
      "nome": "15.png"
    },
    "dirExportar": "/export/[ASSINATURA]/mes-001/semana-3/1-segunda/",
    "prefixo": "P3-C0015"
  },
  {
    "id": "16",
    "modelo": "modelo-conteudo.psd",
    "titulo": [
      "AQUECER É",
      "Preciso"
    ],
    "dirBase": "/base/",
    "imagem": {
      "posicao": "E",
      "girar": "S",
      "nome": "16.png"
    },
    "dirExportar": "/export/[ASSINATURA]/mes-001/semana-3/2-terça/",
    "prefixo": "P3-C0016"
  },
  {
    "id": "17",
    "modelo": "modelo-conteudo.psd",
    "titulo": [
      "EQUILÍBRIO",
      "Muscular"
    ],
    "dirBase": "/base/",
    "imagem": {
      "posicao": "C",
      "girar": "N",
      "nome": "17.png"
    },
    "dirExportar": "/export/[ASSINATURA]/mes-001/semana-3/3-quarta/",
    "prefixo": "P3-C0017"
  },
  {
    "id": "18",
    "modelo": "modelo-conteudo.psd",
    "titulo": [
      "RESPEITE OS",
      "Intervalos"
    ],
    "dirBase": "/base/",
    "imagem": {
      "posicao": "E",
      "girar": "S",
      "nome": "18.png"
    },
    "dirExportar": "/export/[ASSINATURA]/mes-001/semana-3/4-quinta/",
    "prefixo": "P3-C0018"
  },
  {
    "id": "19",
    "modelo": "modelo-conteudo.psd",
    "titulo": [
      "FAÇA ATIVIDADES",
      "Complementares"
    ],
    "dirBase": "/base/",
    "imagem": {
      "posicao": "C",
      "girar": "S",
      "nome": "19.png"
    },
    "dirExportar": "/export/[ASSINATURA]/mes-001/semana-3/5-sexta/",
    "prefixo": "P3-C0019"
  },
  {
    "id": "20",
    "modelo": "modelo-conteudo.psd",
    "titulo": [
      "NOSSAS",
      "Escolhas"
    ],
    "dirBase": "/base/",
    "imagem": {
      "posicao": "C",
      "girar": "N",
      "nome": "20.png"
    },
    "dirExportar": "/export/[ASSINATURA]/mes-001/semana-3/6-sábado/",
    "prefixo": "P3-C0020"
  },
  {
    "id": "21",
    "modelo": "modelo-conteudo.psd",
    "titulo": [
      "FOME",
      "Emocional"
    ],
    "dirBase": "/base/",
    "imagem": {
      "posicao": "C",
      "girar": "N",
      "nome": "21.png"
    },
    "dirExportar": "/export/[ASSINATURA]/mes-001/semana-3/7-domingo/",
    "prefixo": "P3-C0021"
  },
  {
    "id": "22",
    "modelo": "modelo-conteudo.psd",
    "titulo": [
      "COLESTEROL E",
      "Açúcar"
    ],
    "dirBase": "/base/",
    "imagem": {
      "posicao": "C",
      "girar": "N",
      "nome": "22.png"
    },
    "dirExportar": "/export/[ASSINATURA]/mes-001/semana-4/1-segunda/",
    "prefixo": "P3-C0022"
  },
  {
    "id": "23",
    "modelo": "modelo-conteudo.psd",
    "titulo": [
      "PROTEÍNA E",
      "Café da manhã"
    ],
    "dirBase": "/base/",
    "imagem": {
      "posicao": "C",
      "girar": "N",
      "nome": "23.png"
    },
    "dirExportar": "/export/[ASSINATURA]/mes-001/semana-4/2-terça/",
    "prefixo": "P3-C0023"
  },
  {
    "id": "24",
    "modelo": "modelo-conteudo.psd",
    "titulo": [
      "RELACIONAMENTO",
      "Saudável"
    ],
    "dirBase": "/base/",
    "imagem": {
      "posicao": "C",
      "girar": "N",
      "nome": "24.png"
    },
    "dirExportar": "/export/[ASSINATURA]/mes-001/semana-4/3-quarta/",
    "prefixo": "P3-C0024"
  },
  {
    "id": "25",
    "modelo": "modelo-conteudo.psd",
    "titulo": [
      "FIBRAS =",
      "Cintura fina"
    ],
    "dirBase": "/base/",
    "imagem": {
      "posicao": "C",
      "girar": "N",
      "nome": "25.png"
    },
    "dirExportar": "/export/[ASSINATURA]/mes-001/semana-4/4-quinta/",
    "prefixo": "P3-C0025"
  },
  {
    "id": "26",
    "modelo": "modelo-conteudo.psd",
    "titulo": [
      "USAR OU NÃO",
      "Colágeno?"
    ],
    "dirBase": "/base/",
    "imagem": {
      "posicao": "C",
      "girar": "N",
      "nome": "26.png"
    },
    "dirExportar": "/export/[ASSINATURA]/mes-001/semana-4/5-sexta/",
    "prefixo": "P3-C0026"
  },
  {
    "id": "27",
    "modelo": "modelo-conteudo.psd",
    "titulo": [
      "COUVE",
      "Flor"
    ],
    "dirBase": "/base/",
    "imagem": {
      "posicao": "C",
      "girar": "S",
      "nome": "27.png"
    },
    "dirExportar": "/export/[ASSINATURA]/mes-001/semana-4/6-sábado/",
    "prefixo": "P3-C0027"
  },
  {
    "id": "28",
    "modelo": "modelo-conteudo.psd",
    "titulo": [
      "DESEJO OU",
      "Hábito"
    ],
    "dirBase": "/base/",
    "imagem": {
      "posicao": "E",
      "girar": "N",
      "nome": "28.png"
    },
    "dirExportar": "/export/[ASSINATURA]/mes-001/semana-4/7-domingo/",
    "prefixo": "P3-C0028"
  },
  {
    "id": "29",
    "modelo": "modelo-conteudo.psd",
    "titulo": [
      "MALHAR APÓS",
      "os 40"
    ],
    "dirBase": "/base/",
    "imagem": {
      "posicao": "C",
      "girar": "S",
      "nome": "29.png"
    },
    "dirExportar": "/export/[ASSINATURA]/mes-002/semana-1/1-segunda/",
    "prefixo": "P3-C0029"
  },
  {
    "id": "30",
    "modelo": "modelo-conteudo.psd",
    "titulo": [
      "COMO ACABAR COM",
      "a Celulite"
    ],
    "dirBase": "/base/",
    "imagem": {
      "posicao": "E",
      "girar": "S",
      "nome": "30.png"
    },
    "dirExportar": "/export/[ASSINATURA]/mes-002/semana-1/2-terça/",
    "prefixo": "P3-C0030"
  },
  {
    "id": "31",
    "modelo": "modelo-conteudo.psd",
    "titulo": [
      "TRISTEZA E ANSIEDADE",
      "Engorda"
    ],
    "dirBase": "/base/",
    "imagem": {
      "posicao": "E",
      "girar": "N",
      "nome": "31.png"
    },
    "dirExportar": "/export/[ASSINATURA]/mes-002/semana-1/3-quarta/",
    "prefixo": "P3-C0031"
  },
  {
    "id": "32",
    "modelo": "modelo-conteudo.psd",
    "titulo": [
      "DESEJO X",
      "Hábito"
    ],
    "dirBase": "/base/",
    "imagem": {
      "posicao": "C",
      "girar": "N",
      "nome": "32.png"
    },
    "dirExportar": "/export/[ASSINATURA]/mes-002/semana-1/4-quinta/",
    "prefixo": "P3-C0032"
  },
  {
    "id": "33",
    "modelo": "modelo-conteudo.psd",
    "titulo": [
      "GORDURA",
      "no Fígado"
    ],
    "dirBase": "/base/",
    "imagem": {
      "posicao": "C",
      "girar": "N",
      "nome": "33.png"
    },
    "dirExportar": "/export/[ASSINATURA]/mes-002/semana-1/5-sexta/",
    "prefixo": "P3-C0033"
  },
  {
    "id": "34",
    "modelo": "modelo-conteudo.psd",
    "titulo": [
      "EMAGRECIMENTO &",
      "Genética"
    ],
    "dirBase": "/base/",
    "imagem": {
      "posicao": "C",
      "girar": "N",
      "nome": "34.png"
    },
    "dirExportar": "/export/[ASSINATURA]/mes-002/semana-1/6-sábado/",
    "prefixo": "P3-C0034"
  },
  {
    "id": "35",
    "modelo": "modelo-conteudo.psd",
    "titulo": [
      "LIGHT & DIET",
      "Emagrece?"
    ],
    "dirBase": "/base/",
    "imagem": {
      "posicao": "C",
      "girar": "S",
      "nome": "35.png"
    },
    "dirExportar": "/export/[ASSINATURA]/mes-002/semana-1/7-domingo/",
    "prefixo": "P3-C0035"
  },
  {
    "id": "36",
    "modelo": "modelo-conteudo.psd",
    "dirBase": "/base/",
    "imagem": {
      "nome": "36.png"
    },
    "dirExportar": "/export/[ASSINATURA]/mes-002/semana-2/1-segunda/",
    "prefixo": "P3-C0036"
  },
  {
    "id": "37",
    "modelo": "modelo-conteudo.psd",
    "dirBase": "/base/",
    "imagem": {
      "nome": "37.png"
    },
    "dirExportar": "/export/[ASSINATURA]/mes-002/semana-2/2-terça/",
    "prefixo": "P3-C0037"
  },
  {
    "id": "38",
    "modelo": "modelo-conteudo.psd",
    "dirBase": "/base/",
    "imagem": {
      "nome": "38.png"
    },
    "dirExportar": "/export/[ASSINATURA]/mes-002/semana-2/3-quarta/",
    "prefixo": "P3-C0038"
  },
  {
    "id": "39",
    "modelo": "modelo-conteudo.psd",
    "dirBase": "/base/",
    "imagem": {
      "nome": "39.png"
    },
    "dirExportar": "/export/[ASSINATURA]/mes-002/semana-2/4-quinta/",
    "prefixo": "P3-C0039"
  },
  {
    "id": "40",
    "modelo": "modelo-conteudo.psd",
    "dirBase": "/base/",
    "imagem": {
      "nome": "40.png"
    },
    "dirExportar": "/export/[ASSINATURA]/mes-002/semana-2/5-sexta/",
    "prefixo": "P3-C0040"
  },
  {
    "id": "41",
    "modelo": "modelo-conteudo.psd",
    "dirBase": "/base/",
    "imagem": {
      "nome": "41.png"
    },
    "dirExportar": "/export/[ASSINATURA]/mes-002/semana-2/6-sábado/",
    "prefixo": "P3-C0041"
  },
  {
    "id": "42",
    "modelo": "modelo-conteudo.psd",
    "dirBase": "/base/",
    "imagem": {
      "nome": "42.png"
    },
    "dirExportar": "/export/[ASSINATURA]/mes-002/semana-2/7-domingo/",
    "prefixo": "P3-C0042"
  },
  {
    "id": "43",
    "modelo": "modelo-conteudo.psd",
    "dirBase": "/base/",
    "imagem": {
      "nome": "43.png"
    },
    "dirExportar": "/export/[ASSINATURA]/mes-002/semana-3/1-segunda/",
    "prefixo": "P3-C0043"
  },
  {
    "id": "44",
    "modelo": "modelo-conteudo.psd",
    "dirBase": "/base/",
    "imagem": {
      "nome": "44.png"
    },
    "dirExportar": "/export/[ASSINATURA]/mes-002/semana-3/2-terça/",
    "prefixo": "P3-C0044"
  },
  {
    "id": "45",
    "modelo": "modelo-conteudo.psd",
    "dirBase": "/base/",
    "imagem": {
      "nome": "45.png"
    },
    "dirExportar": "/export/[ASSINATURA]/mes-002/semana-3/3-quarta/",
    "prefixo": "P3-C0045"
  },
  {
    "id": "46",
    "modelo": "modelo-conteudo.psd",
    "dirBase": "/base/",
    "imagem": {
      "nome": "46.png"
    },
    "dirExportar": "/export/[ASSINATURA]/mes-002/semana-3/4-quinta/",
    "prefixo": "P3-C0046"
  },
  {
    "id": "47",
    "modelo": "modelo-conteudo.psd",
    "dirBase": "/base/",
    "imagem": {
      "nome": "47.png"
    },
    "dirExportar": "/export/[ASSINATURA]/mes-002/semana-3/5-sexta/",
    "prefixo": "P3-C0047"
  },
  {
    "id": "48",
    "modelo": "modelo-conteudo.psd",
    "dirBase": "/base/",
    "imagem": {
      "nome": "48.png"
    },
    "dirExportar": "/export/[ASSINATURA]/mes-002/semana-3/6-sábado/",
    "prefixo": "P3-C0048"
  },
  {
    "id": "49",
    "modelo": "modelo-conteudo.psd",
    "dirBase": "/base/",
    "imagem": {
      "nome": "49.png"
    },
    "dirExportar": "/export/[ASSINATURA]/mes-002/semana-3/7-domingo/",
    "prefixo": "P3-C0049"
  }
]